odoo9_addon_partner_contact_in_several_companies-9.0.1.0.1-nspkg.pth
odoo_addons/partner_contact_in_several_companies/README.rst
odoo_addons/partner_contact_in_several_companies/__init__.py
odoo_addons/partner_contact_in_several_companies/__openerp__.py
odoo_addons/partner_contact_in_several_companies/demo/ir_actions.xml
odoo_addons/partner_contact_in_several_companies/demo/res_partner.xml
odoo_addons/partner_contact_in_several_companies/i18n/am.po
odoo_addons/partner_contact_in_several_companies/i18n/ar.po
odoo_addons/partner_contact_in_several_companies/i18n/bg.po
odoo_addons/partner_contact_in_several_companies/i18n/bs.po
odoo_addons/partner_contact_in_several_companies/i18n/ca.po
odoo_addons/partner_contact_in_several_companies/i18n/cs.po
odoo_addons/partner_contact_in_several_companies/i18n/da.po
odoo_addons/partner_contact_in_several_companies/i18n/de.po
odoo_addons/partner_contact_in_several_companies/i18n/el_GR.po
odoo_addons/partner_contact_in_several_companies/i18n/en_GB.po
odoo_addons/partner_contact_in_several_companies/i18n/es.po
odoo_addons/partner_contact_in_several_companies/i18n/es_CR.po
odoo_addons/partner_contact_in_several_companies/i18n/es_EC.po
odoo_addons/partner_contact_in_several_companies/i18n/es_ES.po
odoo_addons/partner_contact_in_several_companies/i18n/es_MX.po
odoo_addons/partner_contact_in_several_companies/i18n/es_VE.po
odoo_addons/partner_contact_in_several_companies/i18n/et.po
odoo_addons/partner_contact_in_several_companies/i18n/eu.po
odoo_addons/partner_contact_in_several_companies/i18n/fi.po
odoo_addons/partner_contact_in_several_companies/i18n/fr.po
odoo_addons/partner_contact_in_several_companies/i18n/fr_CA.po
odoo_addons/partner_contact_in_several_companies/i18n/fr_CH.po
odoo_addons/partner_contact_in_several_companies/i18n/gl.po
odoo_addons/partner_contact_in_several_companies/i18n/hr.po
odoo_addons/partner_contact_in_several_companies/i18n/hr_HR.po
odoo_addons/partner_contact_in_several_companies/i18n/hu.po
odoo9_addon_partner_contact_in_several_companies-9.0.1.0.1.dist-info/METADATA
odoo9_addon_partner_contact_in_several_companies-9.0.1.0.1.dist-info/WHEEL
odoo9_addon_partner_contact_in_several_companies-9.0.1.0.1.dist-info/namespace_packages.txt
odoo9_addon_partner_contact_in_several_companies-9.0.1.0.1.dist-info/top_level.txt
odoo9_addon_partner_contact_in_several_companies-9.0.1.0.1.dist-info/RECORD
